pyguest.py
pyguest-0.1.0.dist-info/LICENSE
pyguest-0.1.0.dist-info/WHEEL
pyguest-0.1.0.dist-info/METADATA
pyguest-0.1.0.dist-info/RECORD
